LICENSE
MANIFEST.in
README
pypi2spec.spec
setup.py
pypi2spec/__init__.py
pypi2spec/__init__.pyc
pypi2spec/spec.py
pypi2spec/spec.pyc
pypi2spec/specfile.tpl
pypi2spec.egg-info/PKG-INFO
pypi2spec.egg-info/SOURCES.txt
pypi2spec.egg-info/dependency_links.txt
pypi2spec.egg-info/entry_points.txt
pypi2spec.egg-info/requires.txt
pypi2spec.egg-info/top_level.txt