Metadata-Version: 1.1
Name: pypi2spec
Version: 0.5.0
Summary: Small library to help you generate spec file for pypi project.
Home-page: http://github.com/pypingou/pypi2spec
Author: Pierre-Yves Chibon
Author-email: pingou@pingoured.fr
License: GPLv3+
Download-URL: http://pypi.python.org/packages/source/p/pypi2spec/pypi2spec-0.5.0.tar.gz
Platform: UNKNOWN
Classifier: Programming Language :: Python
Classifier: License :: OSI Approved :: GNU General Public License v3 or later (GPLv3+)
Classifier: Operating System :: OS Independent
Classifier: Development Status :: 5 - Production/Stable
Classifier: Intended Audience :: Developers
Classifier: Environment :: Console
